<?xml version="1.0" encoding="UTF-8"?>
<objects serializationModel="Studio.01.10.00">
    <object class="MixerMaster" id="{46248773-b7ba-4695-9e63-a1eb3f18db70}">
        <property name="name">
            <value>Master Bus</value>
        </property>
        <relationship name="effectChain">
            <destination>{d4edc452-6246-4b6a-a24c-991482af84ff}</destination>
        </relationship>
        <relationship name="panner">
            <destination>{e96414a2-4b8a-4672-b777-c5ca3dabd6ee}</destination>
        </relationship>
        <relationship name="mixer">
            <destination>{21edccf3-4d3d-4b10-9dd0-a6df336208ea}</destination>
        </relationship>
    </object>
    <object class="MixerBusEffectChain" id="{d4edc452-6246-4b6a-a24c-991482af84ff}">
        <relationship name="effects">
            <destination>{ff2a38d6-3d0d-4ad4-ae4a-e64e5c108642}</destination>
        </relationship>
    </object>
    <object class="MixerBusPanner" id="{e96414a2-4b8a-4672-b777-c5ca3dabd6ee}">
        <property name="overridingOutputFormat">
            <value>2</value>
        </property>
        <property name="outputFormatOverridden">
            <value>true</value>
        </property>
    </object>
    <object class="MixerBusFader" id="{ff2a38d6-3d0d-4ad4-ae4a-e64e5c108642}"/>
</objects>
